pyCardiac/__init__.py
pyCardiac/metrics/__init__.py
pyCardiac/metrics/norms.py
pyCardiac/rhythm/__init__.py
pyCardiac/rhythm/binning.py
pyCardiac/rhythm/calculate_APD_map.py
pyCardiac/rhythm/calculate_CV_map.py
pyCardiac/rhythm/calculate_activation_map.py
pyCardiac/rhythm/calculate_alternance_map.py
pyCardiac/rhythm/ensemble_average.py
pyCardiac/rhythm/fourier_filter.py
pyCardiac/rhythm/remove_baseline.py
pyCardiac/rhythm/rescale.py
pyCardiac/rhythm/transform_to_phase.py
pyCardiac/routines/__init__.py
pyCardiac/routines/awgn.py
pyCardiac/routines/kernel_gaussian.py
pyCardiac/routines/routines.py
pyCardiac/signal/__init__.py
pyCardiac/signal/analysis/__init__.py
pyCardiac/signal/analysis/calculate_APD.py
pyCardiac/signal/analysis/calculate_activation_time.py
pyCardiac/signal/analysis/calculate_alternance.py
pyCardiac/signal/analysis/phase_singularity.py
pyCardiac/signal/analysis/snr.py
pyCardiac/signal/processing/__init__.py
pyCardiac/signal/processing/autoscaling.py
pyCardiac/signal/processing/ensemble_average.py
pyCardiac/signal/processing/normalize.py
pyCardiac/signal/processing/remove_baseline.py
pyCardiac/signal/processing/transform_to_phase.py
pyCardiac/signal/processing/filtration/__init__.py
pyCardiac/signal/processing/filtration/binning.py
pyCardiac/signal/processing/filtration/fourier_filter.py
pyCardiac-1.0.1.dist-info/LICENSE
pyCardiac-1.0.1.dist-info/METADATA
pyCardiac-1.0.1.dist-info/WHEEL
pyCardiac-1.0.1.dist-info/top_level.txt
pyCardiac-1.0.1.dist-info/RECORD
