Metadata-Version: 2.1
Name: pyCardiac
Version: 1.0.1
Summary: UNKNOWN
Home-page: https://github.com/humanphysiologylab/pyCardiac
Author: Human Physiology Lab
Author-email: dmitrii.smirnov@phystech.edu
License: MIT
Keywords: Cardiac analysis
Platform: any
Classifier: Development Status :: 3 - Alpha
Classifier: License :: OSI Approved :: MIT License
Classifier: Programming Language :: Python :: 3.0
Classifier: Programming Language :: Python :: 3.5
Classifier: Programming Language :: Python :: 3.6
Classifier: Topic :: Scientific/Engineering :: Medical Science Apps.
Requires-Dist: numpy (>=1.16.2)
Requires-Dist: scipy (>=1.2.1)
